setup.cfg
setup.py
WSME_SQLAlchemy.egg-info/PKG-INFO
WSME_SQLAlchemy.egg-info/SOURCES.txt
WSME_SQLAlchemy.egg-info/dependency_links.txt
WSME_SQLAlchemy.egg-info/requires.txt
WSME_SQLAlchemy.egg-info/top_level.txt
wsmeext/__init__.py
wsmeext/sqlalchemy/__init__.py
wsmeext/sqlalchemy/controllers.py
wsmeext/sqlalchemy/types.py
wsmeext/sqlalchemy/tests/__init__.py
wsmeext/sqlalchemy/tests/test_controllers.py
wsmeext/sqlalchemy/tests/test_types.py